display_status/__init__.py
display_status/display_status.py
display_status-1.0.0.post5.dist-info/LICENSE
display_status-1.0.0.post5.dist-info/METADATA
display_status-1.0.0.post5.dist-info/WHEEL
display_status-1.0.0.post5.dist-info/eager_resources.txt
display_status-1.0.0.post5.dist-info/top_level.txt
display_status-1.0.0.post5.dist-info/RECORD
